stackit/alb/__init__.py
stackit/alb/api/__init__.py
stackit/alb/api/default_api.py
stackit/alb/api_client.py
stackit/alb/api_response.py
stackit/alb/configuration.py
stackit/alb/exceptions.py
stackit/alb/models/__init__.py
stackit/alb/models/active_health_check.py
stackit/alb/models/certificate_config.py
stackit/alb/models/cookie_persistence.py
stackit/alb/models/create_credentials_payload.py
stackit/alb/models/create_credentials_response.py
stackit/alb/models/create_load_balancer_payload.py
stackit/alb/models/credentials_response.py
stackit/alb/models/get_credentials_response.py
stackit/alb/models/get_quota_response.py
stackit/alb/models/google_protobuf_any.py
stackit/alb/models/host_config.py
stackit/alb/models/http_header.py
stackit/alb/models/http_health_checks.py
stackit/alb/models/list_credentials_response.py
stackit/alb/models/list_load_balancers_response.py
stackit/alb/models/list_plans_response.py
stackit/alb/models/listener.py
stackit/alb/models/load_balancer.py
stackit/alb/models/load_balancer_error.py
stackit/alb/models/load_balancer_options.py
stackit/alb/models/loadbalancer_option_access_control.py
stackit/alb/models/loadbalancer_option_logs.py
stackit/alb/models/loadbalancer_option_metrics.py
stackit/alb/models/loadbalancer_option_observability.py
stackit/alb/models/network.py
stackit/alb/models/path.py
stackit/alb/models/plan_details.py
stackit/alb/models/protocol_options_http.py
stackit/alb/models/protocol_options_https.py
stackit/alb/models/query_parameter.py
stackit/alb/models/rule.py
stackit/alb/models/security_group.py
stackit/alb/models/status.py
stackit/alb/models/target.py
stackit/alb/models/target_pool.py
stackit/alb/models/target_pool_tls_config.py
stackit/alb/models/update_credentials_payload.py
stackit/alb/models/update_credentials_response.py
stackit/alb/models/update_load_balancer_payload.py
stackit/alb/models/update_target_pool_payload.py
stackit/alb/py.typed
stackit/alb/rest.py
stackit_alb-0.8.0.dist-info/METADATA
stackit_alb-0.8.0.dist-info/WHEEL
stackit_alb-0.8.0.dist-info/licenses/LICENSE.md
stackit_alb-0.8.0.dist-info/licenses/NOTICE.txt
stackit_alb-0.8.0.dist-info/RECORD
